anieesh/__init__.py
anieesh-0.0.1.dist-info/METADATA
anieesh-0.0.1.dist-info/WHEEL
anieesh-0.0.1.dist-info/top_level.txt
anieesh-0.0.1.dist-info/RECORD
