Metadata-Version: 2.4
Name: anieesh
Version: 0.0.1
Summary: Personal utilities
Author-email: Anieesh <anieesh.saravanan@gmail.com>
License: MIT
Requires-Python: >=3.10
